bottle_restx.py
bottle_restx-1.0.1.dist-info/METADATA
bottle_restx-1.0.1.dist-info/WHEEL
bottle_restx-1.0.1.dist-info/top_level.txt
bottle_restx-1.0.1.dist-info/RECORD
