Metadata-Version: 2.1
Name: bottle-restx
Version: 1.0.1
Summary: A simple resource based REST API extension for the bottle framework
Home-page: https://github.com/bliepp/bottle-restx
Author: bliepp
License: UNKNOWN
Project-URL: Bug Tracker, https://github.com/bliepp/bottle-restx/issues
Platform: UNKNOWN
Classifier: Development Status :: 4 - Beta
Classifier: Topic :: Software Development :: Libraries :: Python Modules
Classifier: Operating System :: OS Independent
Classifier: Intended Audience :: Developers
Classifier: Programming Language :: Python :: 3
Classifier: Programming Language :: Python :: 3.6
Classifier: Programming Language :: Python :: 3.7
Classifier: Programming Language :: Python :: 3.8
Classifier: Programming Language :: Python :: 3.9
Classifier: Programming Language :: Python :: 3.10
Classifier: Topic :: Software Development :: Libraries :: Python Modules
Classifier: License :: OSI Approved :: MIT License
Requires-Python: >=3.6
